psyco_full.py
CPAT-3.0.4.data/scripts/cpat.py
CPAT-3.0.4.data/scripts/make_hexamer_tab.py
CPAT-3.0.4.data/scripts/make_logitModel.py
cpmodule/FrameKmer.py
cpmodule/__init__.py
cpmodule/dotProduct.py
cpmodule/fasta.py
cpmodule/fickett.py
cpmodule/find_orfs.py
cpmodule/ireader.py
cpmodule/orf.py
cpmodule/utils.py
CPAT-3.0.4.dist-info/LICENSE.txt
CPAT-3.0.4.dist-info/METADATA
CPAT-3.0.4.dist-info/WHEEL
CPAT-3.0.4.dist-info/top_level.txt
CPAT-3.0.4.dist-info/RECORD
