Metadata-Version: 2.1
Name: CPAT
Version: 3.0.4
Summary: CPAT (Coding Potential Assessment Tool)
Home-page: http://rna-cpat.sourceforge.net/, https://wlcb.oit.uci.edu/cpat
Author: Liguo Wang, Jung Hyun Park
Author-email: wang.liguo@mayo.edu, wei.li@uci.edu, hj_park@pitt.edu
License: GNU General Public License
Keywords: RNA coding potential prediction,lncRNA,lincRNA,logsitic regression
Platform: Linux
Platform: MacOS
Classifier: Development Status :: 5 - Production/Stable
Classifier: Environment :: Console
Classifier: Intended Audience :: Science/Research
Classifier: License :: OSI Approved :: GNU General Public License v2 (GPLv2)
Classifier: Operating System :: MacOS :: MacOS X
Classifier: Operating System :: POSIX
Classifier: Programming Language :: Python
Classifier: Topic :: Scientific/Engineering :: Bio-Informatics
Requires: cython (>=0.17)
Requires-Python: >=3.5
Requires-Dist: numpy
Requires-Dist: pysam
